{
  "PermissionConfig": {
    "Policies": [
      {
        "Permission": "BrowseUsers",
        "Roles": [ "User", "Shelter", "Admin" ],
        "AffiliatedRoles": []
      },
      {
        "Permission": "EditUsers",
        "Roles": [ "Admin" ],
        "AffiliatedRoles": []
      },
      {
        "Permission": "DeleteUsers",
        "Roles": [ "Admin" ],
        "AffiliatedRoles": []
      },
      {
        "Permission": "BrowseShelters",
        "Roles": [ "User", "Shelter", "Admin" ],
        "AffiliatedRoles": []
      },
      {
        "Permission": "EditShelters",
        "Roles": [ "Admin" ],
        "AffiliatedRoles": []
      },
      {
        "Permission": "DeleteShelters",
        "Roles": [ "Admin" ],
        "AffiliatedRoles": []
      },
      {
        "Permission": "CreateAnimals",
        "Roles": [ "Shelter", "Admin" ],
        "AffiliatedRoles": []
      },
      {
        "Permission": "BrowseAnimals",
        "Roles": [ "User", "Shelter", "Admin" ],
        "AffiliatedRoles": []
      },
      {
        "Permission": "EditAnimals",
        "Roles": [ "Shelter", "Admin" ],
        "AffiliatedRoles": []
      },
      {
        "Permission": "DeleteAnimals",
        "Roles": [ "Admin" ],
        "AffiliatedRoles": []
      },
      {
        "Permission": "CreateAnimalTypes",
        "Roles": [ "Admin" ],
        "AffiliatedRoles": []
      },
      {
        "Permission": "BrowseAnimalTypes",
        "Roles": [ "User", "Shelter", "Admin" ],
        "AffiliatedRoles": []
      },
      {
        "Permission": "EditAnimalTypes",
        "Roles": [ "Admin" ],
        "AffiliatedRoles": []
      },
      {
        "Permission": "DeleteAnimalTypes",
        "Roles": [ "Admin" ],
        "AffiliatedRoles": []
      },
      {
        "Permission": "CreateBreeds",
        "Roles": [ "Admin" ],
        "AffiliatedRoles": []
      },
      {
        "Permission": "BrowseBreeds",
        "Roles": [ "User", "Shelter", "Admin" ],
        "AffiliatedRoles": []
      },
      {
        "Permission": "EditBreeds",
        "Roles": [ "Admin" ],
        "AffiliatedRoles": []
      },
      {
        "Permission": "DeleteBreeds",
        "Roles": [ "Admin" ],
        "AffiliatedRoles": []
      },
      {
        "Permission": "CreateAdoptionApplications",
        "Roles": [ "User", "Shelter", "Admin" ],
        "AffiliatedRoles": []
      },
      {
        "Permission": "BrowseAdoptionApplications",
        "Roles": [ "Admin" ],
        "AffiliatedRoles": []
      },
      {
        "Permission": "EditAdoptionApplications",
        "Roles": [ "Admin" ],
        "AffiliatedRoles": []
      },
      {
        "Permission": "DeleteAdoptionApplications",
        "Roles": [ "Admin" ],
        "AffiliatedRoles": []
      },
      {
        "Permission": "CreateFiles",
        "Roles": [ "User", "Shelter", "Admin" ],
        "AffiliatedRoles": []
      },
      {
        "Permission": "BrowseFiles",
        "Roles": [ "User", "Shelter", "Admin" ],
        "AffiliatedRoles": [ "User", "Shelter" ]
      },
      {
        "Permission": "EditFiles",
        "Roles": [ "Admin" ],
        "AffiliatedRoles": []
      },
      {
        "Permission": "DeleteFiles",
        "Roles": [ "Admin" ],
        "AffiliatedRoles": []
      },
      {
        "Permission": "CreateConversations",
        "Roles": [ "User", "Shelter", "Admin" ],
        "AffiliatedRoles": []
      },
      {
        "Permission": "BrowseConversations",
        "Roles": [ "Admin" ],
        "AffiliatedRoles": [ "User", "Shelter" ]
      },
      {
        "Permission": "EditConversations",
        "Roles": [ "Admin" ],
        "AffiliatedRoles": []
      },
      {
        "Permission": "DeleteConversations",
        "Roles": [ "Admin" ],
        "AffiliatedRoles": []
      },
      {
        "Permission": "CreateMessages",
        "Roles": [ "Admin" ],
        "AffiliatedRoles": [ "User", "Shelter" ]
      },
      {
        "Permission": "BrowseMessages",
        "Roles": [ "Admin" ],
        "AffiliatedRoles": [ "User", "Shelter" ]
      },
      {
        "Permission": "EditMessages",
        "Roles": [ "Admin" ],
        "AffiliatedRoles": [ "User", "Shelter" ]
      },
      {
        "Permission": "DeleteMessages",
        "Roles": [ "Admin" ],
        "AffiliatedRoles": []
      },
      {
        "Permission": "CreateNotifications",
        "Roles": [ "User", "Shelter", "Admin" ],
        "AffiliatedRoles": []
      },
      {
        "Permission": "BrowseNotifications",
        "Roles": [ "Admin" ],
        "AffiliatedRoles": []
      },
      {
        "Permission": "EditNotifications",
        "Roles": [ "Admin" ],
        "AffiliatedRoles": []
      },
      {
        "Permission": "DeleteNotifications",
        "Roles": [ "Admin" ],
        "AffiliatedRoles": []
      },
      {
        "Permission": "CreateReports",
        "Roles": [ "User", "Shelter", "Admin" ],
        "AffiliatedRoles": []
      },
      {
        "Permission": "BrowseReports",
        "Roles": [ "Admin" ],
        "AffiliatedRoles": [ "User", "Shelter" ]
      },
      {
        "Permission": "EditReports",
        "Roles": [ "Admin" ],
        "AffiliatedRoles": []
      },
      {
        "Permission": "DeleteReports",
        "Roles": [ "Admin" ],
        "AffiliatedRoles": []
      }
    ]
  }
}